[
  {
    "title": "Valija digital",
    "description": {
      "es": "Una app para mandar documentos.",
      "en": "An app to send documents."
    },
    "work": { "es": ["El trabajo de Marco"], "en": ["Marco's work"] },
    "technologies": {
      "be": [
        { "id": "java", "version": "8", "important": true },
        { "id": "spring_mvc", "version": "4.3", "important": true },
        { "id": "oracle", "version": "10.2", "important": true },
        { "name": "Spring Security", "version": "4.1" },
        { "name": "Log4j", "version": "1.2" },
        { "name": "Jackson", "version": "1.9" }
      ],
      "fe": [
        { "id": "bootstrap", "version": "3.3", "important": true },
        { "id": "jquery", "version": "3.2", "important": true },
        { "name": "Material Dashboard", "version": "1.2" },
        { "name": "DataTable", "version": "1.10" },
        { "name": "Moment", "version": "2.14" },
        { "name": "Select2", "version": "4.0" },
        { "name": "File Saver", "version": "1.1" },
        { "name": "Sweet Alert 2", "version": "5.3" },
        { "name": "Font Awesome", "version": "4.7" }
      ]
    }
  }
]
